LICENSE.txt
README.md
setup.cfg
setup.py
aws_managers/__init__.py
aws_managers.egg-info/PKG-INFO
aws_managers.egg-info/SOURCES.txt
aws_managers.egg-info/dependency_links.txt
aws_managers.egg-info/requires.txt
aws_managers.egg-info/top_level.txt
aws_managers/athena/__init__.py
aws_managers/athena/athena_frame.py
aws_managers/athena/athena_series.py
aws_managers/athena/tmp.py
aws_managers/athena/clauses/__init__.py
aws_managers/athena/clauses/conjunctive_operators.py
aws_managers/athena/functions/__init__.py
aws_managers/athena/functions/aggregate.py
aws_managers/athena/operators/__init__.py
aws_managers/athena/operators/comparisons.py
aws_managers/athena/operators/mixins.py
aws_managers/athena/queries/__init__.py
aws_managers/athena/queries/athena_column_query_set.py
aws_managers/athena/queries/athena_query_generator.py
aws_managers/athena/queries/boolean_column_query.py
aws_managers/athena/queries/column_query.py
aws_managers/athena/queries/integer_column_query.py
aws_managers/athena/queries/real_column_query.py
aws_managers/athena/queries/string_column_query.py
aws_managers/athena/queries/timestamp_column_query.py
aws_managers/athena/reference/__init__.py
aws_managers/athena/reference/athena_data_types.py
aws_managers/athena/reference/athena_ser_des.py
aws_managers/athena/selectors/__init__.py
aws_managers/athena/selectors/aggregate_selector.py
aws_managers/athena/selectors/case_selector.py
aws_managers/athena/selectors/date_format_selector.py
aws_managers/athena/selectors/tmp.py
aws_managers/converters/__init__.py
aws_managers/converters/dataset_converter.py
aws_managers/feature_store/__init__.py
aws_managers/feature_store/feature_group_manager.py
aws_managers/feature_store/features_metadata.py
aws_managers/feature_store/utils.py
aws_managers/paths/__init__.py
aws_managers/paths/dirs.py
aws_managers/s3/__init__.py
aws_managers/s3/s3_bucket_manager.py
aws_managers/s3/s3_container_mixin.py
aws_managers/s3/s3_folder_manager.py
aws_managers/s3/tmp.py
aws_managers/s3/utils.py
aws_managers/templates/athena/ddl/column_info.jinja2
aws_managers/templates/athena/ddl/create_table.jinja2
aws_managers/templates/athena/ddl/repair_table.jinja2
